tracker_utils-0.1.3.dist-info/METADATA
tracker_utils-0.1.3.dist-info/WHEEL
tracker_utils-0.1.3.dist-info/entry_points.txt
tracker_utils/__init__.py
tracker_utils/__main__.py
tracker_utils/app.py
tracker_utils/cli.py
tracker_utils/commands/__init__.py
tracker_utils/commands/client_test.py
tracker_utils/commands/set_trackers.py
tracker_utils/commands/test.py
tracker_utils/config.py
tracker_utils/functions/__init__.py
tracker_utils/functions/client_test.py
tracker_utils/functions/set_tracker.py
tracker_utils/functions/test.py
tracker_utils/utils/__init__.py
tracker_utils/utils/base.py
tracker_utils/utils/commands.py
tracker_utils/utils/decorators.py
tracker_utils/utils/function_patcher.py
tracker_utils/utils/functions.py
tracker_utils/utils/output.py
tracker_utils-0.1.3.dist-info/RECORD
